{
  "szuperpiac.hu": {
    "label-Terméknév": {
      "label": "Terméknév",
      "type": "label",
      "options": []
    },
    "input-termeknev": {
      "id": "termeknev",
      "name": "termeknev",
      "type": "input",
      "inputType": "text",
      "options": []
    },
    "label-Kategória": {
      "label": "Kategória",
      "type": "label",
      "options": []
    },
    "select-rovatkod": {
      "id": "rovatkod",
      "name": "rovatkod",
      "type": "select",
      "options": [
        {
          "value": "",
          "text": "Válassz!"
        },
        {
          "value": "62",
          "text": "Antik tárgyak, régiségek, retro"
        },
        {
          "value": "1",
          "text": "Állat, növény"
        },
        {
          "value": "65",
          "text": "Állás, munka (Keres)"
        },
        {
          "value": "7",
          "text": "Állás, munka (Kínál)"
        },
        {
          "value": "93",
          "text": "Állás, munka (Külföldi munkák)"
        },
        {
          "value": "2",
          "text": "Baba és gyermek"
        },
        {
          "value": "89",
          "text": "Befektetés"
        },
        {
          "value": "3",
          "text": "Bútor, lakberendezés"
        },
        {
          "value": "61",
          "text": "CD, DVD"
        },
        {
          "value": "4",
          "text": "Cserebere"
        },
        {
          "value": "5",
          "text": "Egyéb termékek"
        },
        {
          "value": "81",
          "text": "Elektronikai alkatrészek"
        },
        {
          "value": "78",
          "text": "Életjáradék, eltartás"
        },
        {
          "value": "27",
          "text": "Életmód"
        },
        {
          "value": "68",
          "text": "Elveszett, keresem"
        },
        {
          "value": "66",
          "text": "Építkezés, építőanyag"
        },
        {
          "value": "50",
          "text": "Étel, ital"
        },
        {
          "value": "80",
          "text": "Ezotéria"
        },
        {
          "value": "8",
          "text": "Fotó, video"
        },
        {
          "value": "83",
          "text": "Fürdőszoba felszerelés"
        },
        {
          "value": "9",
          "text": "Gép, szerszám"
        },
        {
          "value": "10",
          "text": "GPS, navigáció"
        },
        {
          "value": "11",
          "text": "Gyűjtemények"
        },
        {
          "value": "12",
          "text": "Hangszer, kotta"
        },
        {
          "value": "59",
          "text": "Hardver-szoftver"
        },
        {
          "value": "85",
          "text": "Háztartási cikkek"
        },
        {
          "value": "14",
          "text": "Háztartási gépek"
        },
        {
          "value": "52",
          "text": "Hirdetés - reklám"
        },
        {
          "value": "69",
          "text": "Hobbi, szabadidő"
        },
        {
          "value": "57",
          "text": "Ingatlan - albérlet"
        },
        {
          "value": "58",
          "text": "Ingatlan - bérbeadás (cégek)"
        },
        {
          "value": "41",
          "text": "Ingatlan - egyéb"
        },
        {
          "value": "40",
          "text": "Ingatlan - garázs"
        },
        {
          "value": "15",
          "text": "Ingatlan - ház"
        },
        {
          "value": "79",
          "text": "Ingatlan - iroda, üzlethelyiség"
        },
        {
          "value": "37",
          "text": "Ingatlan - lakás"
        },
        {
          "value": "86",
          "text": "Ingatlan - lakáscsere"
        },
        {
          "value": "39",
          "text": "Ingatlan - nyaraló"
        },
        {
          "value": "38",
          "text": "Ingatlan - telek"
        },
        {
          "value": "76",
          "text": "Ingyen elvihető"
        },
        {
          "value": "16",
          "text": "Internet szolgáltatások"
        },
        {
          "value": "17",
          "text": "Iroda- és biztonságtechnika"
        },
        {
          "value": "46",
          "text": "Jármű - alkatrész"
        },
        {
          "value": "48",
          "text": "Jármű - egyéb"
        },
        {
          "value": "47",
          "text": "Jármű - gumi/felni"
        },
        {
          "value": "42",
          "text": "Jármű - haszonjármű"
        },
        {
          "value": "91",
          "text": "Jármű - kerékpár"
        },
        {
          "value": "45",
          "text": "Jármű - lakókocsi"
        },
        {
          "value": "54",
          "text": "Jármű - légijármű"
        },
        {
          "value": "43",
          "text": "Jármű - motorkerékpár, robogó"
        },
        {
          "value": "92",
          "text": "Jármű - sport, tuning"
        },
        {
          "value": "18",
          "text": "Jármű - személyautó"
        },
        {
          "value": "77",
          "text": "Jármű - veterán jármű"
        },
        {
          "value": "51",
          "text": "Jármű - vizijármű"
        },
        {
          "value": "53",
          "text": "Játék"
        },
        {
          "value": "87",
          "text": "Keresek... (egyedi dolgok)"
        },
        {
          "value": "67",
          "text": "Kert"
        },
        {
          "value": "74",
          "text": "Kommunikáció"
        },
        {
          "value": "19",
          "text": "Konzol játékok (psx,x-box, sega)"
        },
        {
          "value": "88",
          "text": "Környezetbarát termékek (Bio)"
        },
        {
          "value": "34",
          "text": "Kultúra, könyv"
        },
        {
          "value": "60",
          "text": "Laptop (Notebook)"
        },
        {
          "value": "90",
          "text": "Masszázs, gyógymasszázs"
        },
        {
          "value": "75",
          "text": "Mezőgazdaság"
        },
        {
          "value": "20",
          "text": "Mobiltelefonok"
        },
        {
          "value": "64",
          "text": "Modellek, makettek"
        },
        {
          "value": "63",
          "text": "Műszaki cikk"
        },
        {
          "value": "56",
          "text": "Művészeti alkotások, festmények"
        },
        {
          "value": "44",
          "text": "Nyári ajánlatok"
        },
        {
          "value": "72",
          "text": "Oktatás - Egyéb"
        },
        {
          "value": "35",
          "text": "Oktatás - Nyelv"
        },
        {
          "value": "71",
          "text": "Oktatás - Zene"
        },
        {
          "value": "22",
          "text": "Óra - ékszer"
        },
        {
          "value": "70",
          "text": "Programok, rendezvények, party-k"
        },
        {
          "value": "24",
          "text": "Ruházat"
        },
        {
          "value": "25",
          "text": "Sporteszközök"
        },
        {
          "value": "26",
          "text": "Szépség, divat"
        },
        {
          "value": "36",
          "text": "Szex, erotika (18+)"
        },
        {
          "value": "29",
          "text": "Szolgáltatás"
        },
        {
          "value": "30",
          "text": "Szórakozás, kikapcsolódás"
        },
        {
          "value": "31",
          "text": "Szórakoztató elektronika"
        },
        {
          "value": "49",
          "text": "Társkeresés"
        },
        {
          "value": "32",
          "text": "Utazás, turizmus"
        },
        {
          "value": "33",
          "text": "Üzlet, cég, vállalkozás"
        },
        {
          "value": "55",
          "text": "Wellness, egészség"
        }
      ]
    },
    "label-Hely": {
      "label": "Hely",
      "type": "label",
      "options": []
    },
    "input-telepules": {
      "id": "myInput",
      "name": "telepules",
      "type": "input",
      "inputType": "text",
      "options": []
    },
    "label-Ára": {
      "label": "Ára",
      "type": "label",
      "options": []
    },
    "input-ara": {
      "id": "ara",
      "name": "ara",
      "type": "input",
      "inputType": "text",
      "options": []
    },
    "label-Ha 0 Ft-ot adsz meg, akkor nem jelenik meg ár.": {
      "label": "Ha 0 Ft-ot adsz meg, akkor nem jelenik meg ár.",
      "type": "label",
      "options": []
    },
    "label-Hirdetés szövege": {
      "label": "Hirdetés szövege",
      "type": "label",
      "options": []
    },
    "textarea-maxcharfield": {
      "id": "maxcharfield",
      "name": "maxcharfield",
      "type": "textarea",
      "options": []
    },
    "label-Weboldal": {
      "label": "Weboldal",
      "type": "label",
      "options": []
    },
    "input-url": {
      "id": "url",
      "name": "url",
      "type": "input",
      "inputType": "text",
      "options": []
    },
    "label-Kép csatolása (JPG formátum, max. 2 MB fájlméret)": {
      "label": "Kép csatolása (JPG formátum, max. 2 MB fájlméret)",
      "type": "label",
      "options": []
    },
    "label-Kép:": {
      "label": "Kép:",
      "type": "label",
      "options": []
    },
    "input-file": {
      "id": "file",
      "name": "file",
      "type": "input",
      "inputType": "file",
      "options": []
    },
    "div-fileError": {
      "id": "fileError",
      "type": "div",
      "options": []
    },
    "label-Név*": {
      "label": "Név*",
      "type": "label",
      "options": []
    },
    "input-nev": {
      "id": "nev",
      "name": "nev",
      "type": "input",
      "inputType": "text",
      "options": []
    },
    "input-email": {
      "id": "email",
      "name": "email",
      "type": "input",
      "inputType": "hidden",
      "options": []
    },
    "label-Telefon": {
      "label": "Telefon",
      "type": "label",
      "options": []
    },
    "input-tel": {
      "id": "tel",
      "name": "tel",
      "type": "input",
      "inputType": "text",
      "options": []
    },
    "label-A hirdetés feltöltése -a kép méretétől függően- néhány percig is eltarthat!": {
      "label": "A hirdetés feltöltése -a kép méretétől függően- néhány percig is eltarthat!",
      "type": "label",
      "options": []
    }
  }
}